oo_tools/__init__.py
oo_tools/chain.py
oo_tools/save.py
oo_tools/singleton.py
test/__init__.py
test/test_chain.py
test/test_save.py
test/test_singleton.py
oo_tools-0.3.0.dist-info/LICENSE
oo_tools-0.3.0.dist-info/METADATA
oo_tools-0.3.0.dist-info/WHEEL
oo_tools-0.3.0.dist-info/top_level.txt
oo_tools-0.3.0.dist-info/RECORD
